smartWebScraper/__init__.py
smartWebScraper/smartWebScraper.py
smartWebScraper-1.0.0.dist-info/LICENSE.txt
smartWebScraper-1.0.0.dist-info/METADATA
smartWebScraper-1.0.0.dist-info/WHEEL
smartWebScraper-1.0.0.dist-info/top_level.txt
smartWebScraper-1.0.0.dist-info/RECORD
