Metadata-Version: 2.1
Name: smartWebScraper
Version: 1.0.0
Summary: A package that allows you to smartly scrape data from a web page and export it to a CSV file.
Home-page: https://github.com/danysrour/smartWebScraper
Author: Dany Srour
Author-email: dany.srour@gmail.com
Classifier: Development Status :: 5 - Production/Stable
Classifier: Intended Audience :: Developers
Classifier: License :: OSI Approved :: MIT License
Classifier: Programming Language :: Python :: 3
Classifier: Programming Language :: Python :: 3.6
Classifier: Programming Language :: Python :: 3.7
Classifier: Programming Language :: Python :: 3.8
Classifier: Programming Language :: Python :: 3.9
Requires-Python: >=3.6
License-File: LICENSE.txt
Requires-Dist: beautifulsoup4 (>=4.12.2)
Requires-Dist: python-dateutil (>=2.8.2)
Requires-Dist: requests (>=2.31.0)
